nxtb/__init__.py
nxtb/cli.py
nxtb/nxbot.py
nxtb/nxtb.py
nxtb/timestamps.py
nxtb-1.0.3.dist-info/METADATA
nxtb-1.0.3.dist-info/WHEEL
nxtb-1.0.3.dist-info/entry_points.txt
nxtb-1.0.3.dist-info/RECORD
