Metadata-Version: 2.1
Name: nxtb
Version: 1.0.3
Summary: Access the Nextbike API
Requires-Dist: requests
